easysparkcli/__init__.py
easysparkcli/__main__.py
easysparkcli/subcommands/__init__.py
easysparkcli/subcommands/clusterdelete.py
easysparkcli/subcommands/clusterinit.py
easysparkcli/subcommands/submit.py
easysparkcli/subcommands/template.py
easysparkcli/subcommands/validate.py
easysparkcli/subcommands/auxiliar/__init__.py
easysparkcli/subcommands/auxiliar/conf.py
easysparkcli/subcommands/auxiliar/exceptions.py
easysparkcli/subcommands/auxiliar/utils.py
easysparkcli/subcommands/auxiliar/validations.py
easysparkcli-1.0.0.dist-info/LICENSE
easysparkcli-1.0.0.dist-info/METADATA
easysparkcli-1.0.0.dist-info/WHEEL
easysparkcli-1.0.0.dist-info/entry_points.txt
easysparkcli-1.0.0.dist-info/top_level.txt
easysparkcli-1.0.0.dist-info/RECORD
