Metadata-Version: 2.1
Name: easysparkcli
Version: 1.0.0
Summary: Command Line Tool created with the purpose of ease the use of Apache Spark, allowing users to deploy/delete a Spark Cluster and submit batch jobs easily through different options.
Author: Adrian Rodriguez Couto
Author-email: adrian.rcouto@udc.es
License: UNKNOWN
Keywords: spark python cli package automation automice deployment
Platform: UNKNOWN
Classifier: Programming Language :: Python :: 3
Classifier: Programming Language :: Python :: 3.6
Classifier: Programming Language :: Python :: 3.7
Classifier: Programming Language :: Python :: 3.8
Classifier: Programming Language :: Python :: 3.9
Classifier: License :: OSI Approved :: GNU General Public License v3 (GPLv3)
Classifier: Operating System :: OS Independent
Requires-Python: >=3.6
License-File: LICENSE
Requires-Dist: click (>=8.0.3)
Requires-Dist: schema (>=0.7.5)
Requires-Dist: configparser (>=5.2.0)
Requires-Dist: kubernetes (>=21.7.0)
Requires-Dist: python-vagrant (>=0.5.15)
Requires-Dist: pyyaml (>=5.4.1)
